CMakeLists.txt
LICENSE
MANIFEST.in
README.md
setup.py
include/tricubic.hpp
src/tricubic.cpp
tests/__init__.py
tests/simple_test.py
thirdparty/eigen3/.gitignore
thirdparty/eigen3/.hg_archival.txt
thirdparty/eigen3/.hgeol
thirdparty/eigen3/.hgignore
thirdparty/eigen3/.hgtags
thirdparty/eigen3/CMakeLists.txt
thirdparty/eigen3/COPYING.APACHE
thirdparty/eigen3/COPYING.BSD
thirdparty/eigen3/COPYING.GPL
thirdparty/eigen3/COPYING.LGPL
thirdparty/eigen3/COPYING.MINPACK
thirdparty/eigen3/COPYING.MPL2
thirdparty/eigen3/COPYING.README
thirdparty/eigen3/CTestConfig.cmake
thirdparty/eigen3/CTestCustom.cmake.in
thirdparty/eigen3/INSTALL
thirdparty/eigen3/README.md
thirdparty/eigen3/eigen3.pc.in
thirdparty/eigen3/signature_of_eigen3_matrix_library
thirdparty/eigen3/Eigen/Cholesky
thirdparty/eigen3/Eigen/CholmodSupport
thirdparty/eigen3/Eigen/Core
thirdparty/eigen3/Eigen/Dense
thirdparty/eigen3/Eigen/Eigen
thirdparty/eigen3/Eigen/Eigenvalues
thirdparty/eigen3/Eigen/Geometry
thirdparty/eigen3/Eigen/Householder
thirdparty/eigen3/Eigen/IterativeLinearSolvers
thirdparty/eigen3/Eigen/Jacobi
thirdparty/eigen3/Eigen/KLUSupport
thirdparty/eigen3/Eigen/LU
thirdparty/eigen3/Eigen/MetisSupport
thirdparty/eigen3/Eigen/OrderingMethods
thirdparty/eigen3/Eigen/PaStiXSupport
thirdparty/eigen3/Eigen/PardisoSupport
thirdparty/eigen3/Eigen/QR
thirdparty/eigen3/Eigen/QtAlignedMalloc
thirdparty/eigen3/Eigen/SPQRSupport
thirdparty/eigen3/Eigen/SVD
thirdparty/eigen3/Eigen/Sparse
thirdparty/eigen3/Eigen/SparseCholesky
thirdparty/eigen3/Eigen/SparseCore
thirdparty/eigen3/Eigen/SparseLU
thirdparty/eigen3/Eigen/SparseQR
thirdparty/eigen3/Eigen/StdDeque
thirdparty/eigen3/Eigen/StdList
thirdparty/eigen3/Eigen/StdVector
thirdparty/eigen3/Eigen/SuperLUSupport
thirdparty/eigen3/Eigen/UmfPackSupport
thirdparty/eigen3/Eigen/src/Cholesky/LDLT.h
thirdparty/eigen3/Eigen/src/Cholesky/LLT.h
thirdparty/eigen3/Eigen/src/Cholesky/LLT_LAPACKE.h
thirdparty/eigen3/Eigen/src/CholmodSupport/CholmodSupport.h
tricubic.egg-info/PKG-INFO
tricubic.egg-info/SOURCES.txt
tricubic.egg-info/dependency_links.txt
tricubic.egg-info/not-zip-safe
tricubic.egg-info/top_level.txt