Metadata-Version: 2.4
Name: tricubic
Version: 1.0.5
Summary: A tricubic interpolation module for python.
Home-page: https://github.com/danielguterding/pytricubic
Author: Daniel Guterding
Author-email: daniel.guterding@gmail.com
License: MIT
Keywords: tricubic cubic interpolation
License-File: LICENSE
Dynamic: author
Dynamic: author-email
Dynamic: description
Dynamic: description-content-type
Dynamic: home-page
Dynamic: keywords
Dynamic: license
Dynamic: license-file
Dynamic: summary
